pgallery/.mypy_cache/.gitignore
pgallery/.mypy_cache/3.12/@plugins_snapshot.json
pgallery/.mypy_cache/3.12/PIL/ExifTags.data.json
pgallery/.mypy_cache/3.12/PIL/ExifTags.meta.json
pgallery/.mypy_cache/3.12/PIL/GimpGradientFile.data.json
pgallery/.mypy_cache/3.12/PIL/GimpGradientFile.meta.json
pgallery/.mypy_cache/3.12/PIL/GimpPaletteFile.data.json
pgallery/.mypy_cache/3.12/PIL/GimpPaletteFile.meta.json
pgallery/.mypy_cache/3.12/PIL/Image.data.json
pgallery/.mypy_cache/3.12/PIL/Image.meta.json
pgallery/.mypy_cache/3.12/PIL/ImageCms.data.json
pgallery/.mypy_cache/3.12/PIL/ImageCms.meta.json
pgallery/.mypy_cache/3.12/PIL/ImageColor.data.json
pgallery/.mypy_cache/3.12/PIL/ImageColor.meta.json
pgallery/.mypy_cache/3.12/PIL/ImageFile.data.json
pgallery/.mypy_cache/3.12/PIL/ImageFile.meta.json
pgallery/.mypy_cache/3.12/PIL/ImageFilter.data.json
pgallery/.mypy_cache/3.12/PIL/ImageFilter.meta.json
pgallery/.mypy_cache/3.12/PIL/ImageMode.data.json
pgallery/.mypy_cache/3.12/PIL/ImageMode.meta.json
pgallery/.mypy_cache/3.12/PIL/ImageOps.data.json
pgallery/.mypy_cache/3.12/PIL/ImageOps.meta.json
pgallery/.mypy_cache/3.12/PIL/ImagePalette.data.json
pgallery/.mypy_cache/3.12/PIL/ImagePalette.meta.json
pgallery/.mypy_cache/3.12/PIL/ImageQt.data.json
pgallery/.mypy_cache/3.12/PIL/ImageQt.meta.json
pgallery/.mypy_cache/3.12/PIL/PaletteFile.data.json
pgallery/.mypy_cache/3.12/PIL/PaletteFile.meta.json
pgallery/.mypy_cache/3.12/PIL/TiffImagePlugin.data.json
pgallery/.mypy_cache/3.12/PIL/TiffImagePlugin.meta.json
pgallery/.mypy_cache/3.12/PIL/TiffTags.data.json
pgallery/.mypy_cache/3.12/PIL/TiffTags.meta.json
pgallery/.mypy_cache/3.12/PIL/__init__.data.json
pgallery/.mypy_cache/3.12/PIL/__init__.meta.json
pgallery/.mypy_cache/3.12/PIL/_binary.data.json
pgallery/.mypy_cache/3.12/PIL/_binary.meta.json
pgallery/.mypy_cache/3.12/PIL/_deprecate.data.json
pgallery/.mypy_cache/3.12/PIL/_deprecate.meta.json
pgallery/.mypy_cache/3.12/PIL/_imaging.data.json
django_pgallery-0.12.dist-info/WHEEL
django_pgallery-0.12.dist-info/METADATA
django_pgallery-0.12.dist-info/RECORD
