Metadata-Version: 2.3
Name: django-pgallery
Version: 0.12
Summary: Photo gallery app for PostgreSQL and Django.
Author: Zbigniew Siciarz
Author-email: Zbigniew Siciarz <zbigniew@siciarz.net>
Classifier: Development Status :: 3 - Alpha
Classifier: Environment :: Web Environment
Classifier: Framework :: Django
Classifier: Intended Audience :: Developers
Classifier: License :: OSI Approved :: MIT License
Classifier: Operating System :: OS Independent
Classifier: Programming Language :: Python
Classifier: Programming Language :: Python :: 3
Classifier: Programming Language :: Python :: 3.10
Classifier: Programming Language :: Python :: 3.11
Classifier: Programming Language :: Python :: 3.12
Classifier: Programming Language :: Python :: 3.13
Classifier: Framework :: Django
Classifier: Framework :: Django :: 4.2
Classifier: Framework :: Django :: 5.0
Classifier: Framework :: Django :: 5.1
Classifier: Framework :: Django :: 5.2
Classifier: Topic :: Utilities
Requires-Dist: django>=4.2
Requires-Dist: django-markitup>=4.1
Requires-Dist: django-model-utils>=5.0
Requires-Dist: markdown>=3.7
Requires-Dist: pillow>=11.0
Requires-Dist: psycopg>=3.0
Requires-Python: >=3.10
Project-URL: Changelog, https://github.com/zsiciarz/django-pgallery/blob/master/CHANGES.rst
Project-URL: Issues, https://github.com/zsiciarz/django-pgallery/issues
Project-URL: Repository, https://github.com/zsiciarz/django-pgallery
